oe_geoutils/__init__.py
oe_geoutils/renderer.py
oe_geoutils/utils.py
oe_geoutils/data/__init__.py
oe_geoutils/data/mappers.py
oe_geoutils/data/models.py
oe_geoutils/fixtures/vlaams_gewest.geojson
oe_geoutils/fixtures/vlaams_gewest_getijdenzone.geojson
oe_geoutils/validation/__init__.py
oe_geoutils/validation/validators_address.py
oe_geoutils/validation/validators_cadaster_parcels.py
oe_geoutils/validation/validators_contour.py
oe_geoutils/validation/validators_location_elements.py
oe_geoutils/views/__init__.py
oe_geoutils/views/exceptions.py
tests/__init__.py
tests/conftest.py
tests/test_functional.py
tests/test_mappers.py
tests/test_models.py
tests/test_renderer.py
tests/test_utils.py
tests/test_validators_address.py
tests/test_validators_cadaster_parcels.py
tests/test_validators_contour.py
tests/test_validators_location_elements.py
tests/testdata.py
oe_geoutils-1.7.5.dist-info/METADATA
oe_geoutils-1.7.5.dist-info/WHEEL
oe_geoutils-1.7.5.dist-info/entry_points.txt
oe_geoutils-1.7.5.dist-info/top_level.txt
oe_geoutils-1.7.5.dist-info/RECORD
