Metadata-Version: 2.1
Name: oe-geoutils
Version: 1.7.5
Summary: Utility Library
Home-page: https://github.com/OnroerendErfgoed/oe_geoutils
Author: Flanders Heritage Agency
Author-email: ict@onroerenderfgoed.be
License: MIT
Keywords: geoloc
Platform: UNKNOWN
Classifier: Development Status :: 3 - Alpha
Classifier: Intended Audience :: Developers
Classifier: Topic :: Utilities
Classifier: License :: OSI Approved :: MIT License
Classifier: Programming Language :: Python :: 2
Classifier: Programming Language :: Python :: 2.7
Classifier: Programming Language :: Python :: 3
Classifier: Programming Language :: Python :: 3.3
Classifier: Programming Language :: Python :: 3.4
Requires-Dist: Shapely
Requires-Dist: colander
Requires-Dist: crabpy
Requires-Dist: crabpy-pyramid
Requires-Dist: geoalchemy2
Requires-Dist: geojson (<2.5.0)
Requires-Dist: oe-utils (>=1.5.0)
Requires-Dist: pycountry (<=18.5.26)
Requires-Dist: pyproj
Requires-Dist: pyramid
Requires-Dist: requests
